pvshadesim/__init__.py
pvshadesim/plotting.py
pvshadesim/pvelectric.py
pvshadesim/pvmod.py
pvshadesim/pvshade.py
pvshadesim/pvsim.py
pvshadesim/utils.py
pvshadesim/version.py
pvshadesim/data/Plastic_Fern_2p0.pickle
pvshadesim/data/Updated_Plastic_Fern.pickle
pvshadesim/db/PVMM_cell_params_DB.csv
pvshadesim/db/PVMM_mod_params_DB.csv
pvshadesim/db/PVMM_shade_params_DB.csv
pvshadesim/db/Sim_Config.csv
pvshadesim/db/User_cell_index_maps.xlsx
pvshadesim/db/User_cell_pos.xlsx
pvshadesim/db/__init__.py
pvshadesim/db/database.py
pvshadesim-0.0.8.dist-info/licenses/LICENSE
pvshadesim-0.0.8.dist-info/METADATA
pvshadesim-0.0.8.dist-info/WHEEL
pvshadesim-0.0.8.dist-info/top_level.txt
pvshadesim-0.0.8.dist-info/RECORD
