Metadata-Version: 2.4
Name: pvshadesim
Version: 0.0.8
Summary: A physical and electrical shade model using Shapely and PVMismatch.
Author-email: Kiran Balasubramanian <kiran.balasubramanian@maxeon.com>
Maintainer-email: Kiran Balasubramanian <kiran.balasubramanian@maxeon.com>
Project-URL: Homepage, https://github.com/Maxeon-RnD/PVShadeSim
Project-URL: Issues, https://github.com/Maxeon-RnD/PVShadeSim/issues
Keywords: pvmismatch,PV,shading,mismatch,IV,shapely
Classifier: Programming Language :: Python :: 3
Classifier: License :: OSI Approved :: MIT License
Classifier: Operating System :: OS Independent
License-File: LICENSE
Requires-Dist: numpy
Requires-Dist: pandas
Requires-Dist: openpyxl
Requires-Dist: v_pvmismatch
Requires-Dist: shapely
Requires-Dist: matplotlib
Requires-Dist: seaborn
Requires-Dist: plotly
Requires-Dist: dataframe_image
Dynamic: license-file
